certbot_dns_buddy_internal/__init__.py
certbot_dns_buddy_internal/dns_internal.py
certbot_dns_buddy_internal/dns_internal_test.py
certbot_dns_buddy_internal-1.0.1.dist-info/licenses/LICENSE
certbot_dns_buddy_internal-1.0.1.dist-info/METADATA
certbot_dns_buddy_internal-1.0.1.dist-info/WHEEL
certbot_dns_buddy_internal-1.0.1.dist-info/entry_points.txt
certbot_dns_buddy_internal-1.0.1.dist-info/top_level.txt
certbot_dns_buddy_internal-1.0.1.dist-info/RECORD
