Metadata-Version: 2.4
Name: certbot-dns-buddy-internal
Version: 1.0.1
Summary: Buddy DNS internal Authenticator plugin for Certbot
Author: Michal Hankus
License-Expression: Apache-2.0
Classifier: Development Status :: 3 - Alpha
Classifier: Environment :: Plugins
Requires-Python: >=3.9
License-File: LICENSE
Requires-Dist: certbot>=0.31.0
Requires-Dist: setuptools
Requires-Dist: requests
Requires-Dist: requests-mock
Requires-Dist: idna
Dynamic: license-file
